setup.cfg
setup.py
cilenisapi/__init__.py
cilenisapi/client.py
cilenisapi/exceptions.py
python_cilenisapi.egg-info/PKG-INFO
python_cilenisapi.egg-info/SOURCES.txt
python_cilenisapi.egg-info/dependency_links.txt
python_cilenisapi.egg-info/top_level.txt
python_cilenisapi.egg-info/zip-safe