Metadata-Version: 1.0
Name: python-cilenisapi
Version: 0.0.1
Summary: Cilenisapi API client
Home-page: https://github.com/aabilio/python-cilenisapi
Author: aabilio, Weknow Creative Lab
Author-email: aabilio@gmail.com
License: MIT
Keywords: cilenisapi,cilenis
Platform: UNKNOWN
